[
  {
    "route": "/siklus-hidup",
    "firstLoadUncompressedJsBytes": 560366,
    "firstLoadChunkPaths": [
      ".next\\static\\chunks\\05-c3ty_6dwfk.js",
      ".next\\static\\chunks\\14mrh2-p_w84d.js",
      ".next\\static\\chunks\\43f0-kc-dsjr0.js",
      ".next\\static\\chunks\\0iq1i69206cyl.js",
      ".next\\static\\chunks\\0xhu-pfsyvbmx.js",
      ".next\\static\\chunks\\0iec5q4ack_04.js",
      ".next\\static\\chunks\\turbopack-2_5vur9erilgh.js"
    ]
  },
  {
    "route": "/",
    "firstLoadUncompressedJsBytes": 556480,
    "firstLoadChunkPaths": [
      ".next\\static\\chunks\\05-c3ty_6dwfk.js",
      ".next\\static\\chunks\\14mrh2-p_w84d.js",
      ".next\\static\\chunks\\0e5wao6f5_eid.js",
      ".next\\static\\chunks\\0iq1i69206cyl.js",
      ".next\\static\\chunks\\0xhu-pfsyvbmx.js",
      ".next\\static\\chunks\\0iec5q4ack_04.js",
      ".next\\static\\chunks\\turbopack-2_5vur9erilgh.js"
    ]
  },
  {
    "route": "/topik",
    "firstLoadUncompressedJsBytes": 548630,
    "firstLoadChunkPaths": [
      ".next\\static\\chunks\\05-c3ty_6dwfk.js",
      ".next\\static\\chunks\\14mrh2-p_w84d.js",
      ".next\\static\\chunks\\31y5-p8q-uoya.js",
      ".next\\static\\chunks\\0iq1i69206cyl.js",
      ".next\\static\\chunks\\0xhu-pfsyvbmx.js",
      ".next\\static\\chunks\\0iec5q4ack_04.js",
      ".next\\static\\chunks\\turbopack-2_5vur9erilgh.js"
    ]
  },
  {
    "route": "/tentang",
    "firstLoadUncompressedJsBytes": 537044,
    "firstLoadChunkPaths": [
      ".next\\static\\chunks\\05-c3ty_6dwfk.js",
      ".next\\static\\chunks\\14mrh2-p_w84d.js",
      ".next\\static\\chunks\\10hmhcfop_k9n.js",
      ".next\\static\\chunks\\0iq1i69206cyl.js",
      ".next\\static\\chunks\\0xhu-pfsyvbmx.js",
      ".next\\static\\chunks\\0iec5q4ack_04.js",
      ".next\\static\\chunks\\turbopack-2_5vur9erilgh.js"
    ]
  },
  {
    "route": "/_not-found",
    "firstLoadUncompressedJsBytes": 513955,
    "firstLoadChunkPaths": [
      ".next\\static\\chunks\\05-c3ty_6dwfk.js",
      ".next\\static\\chunks\\14mrh2-p_w84d.js",
      ".next\\static\\chunks\\0iq1i69206cyl.js",
      ".next\\static\\chunks\\0xhu-pfsyvbmx.js",
      ".next\\static\\chunks\\0iec5q4ack_04.js",
      ".next\\static\\chunks\\turbopack-2_5vur9erilgh.js"
    ]
  }
]